genruler/__init__.py
genruler/common.py
genruler/exceptions.py
genruler/lexer.py
genruler/library.py
genruler/modules/basic.py
genruler/modules/boolean.py
genruler/modules/condition.py
genruler/modules/list.py
genruler/modules/number.py
genruler/modules/string.py
genruler-0.2.0.dist-info/LICENSE
genruler-0.2.0.dist-info/METADATA
genruler-0.2.0.dist-info/WHEEL
genruler-0.2.0.dist-info/RECORD
