Metadata-Version: 2.1
Name: genruler
Version: 0.2.0
Summary: 
Author: Jeffrey04
Author-email: mycyberpet@yahoo.com
Requires-Python: >=3.12,<4.0
Classifier: Programming Language :: Python :: 3
Classifier: Programming Language :: Python :: 3.12
Classifier: Programming Language :: Python :: 3.13
Requires-Dist: funcparserlib (>=1.0.1,<2.0.0)
